Workbook

Sheet OrdRecaudo
A1: SOLICITUD ORDMARS DE RECAUDO - CWL 2026
A2: # | B2: PRODUCTO | C2: ID VENDEDOR | D2: PROMOTOR | E2: CLIENTE | F2: ID CLIENTE | G2: CECO | H2: CORREO FACTURACIÓN | I2: OBSERVACIÓN | J2: MES A FACTURAR | K2: DÍAS DE CONCESIÓN | L2: VALOR DÍA (Sin IVA) | M2: V.SUBTOTAL (Sin IVA) | N2: VALOR TOTAL (IVA incluido) | O2: FECHA 1 LÍMITE pago | P2: DIRECCIÓN | Q2: ¿ES AFILIADO?
A3: 1 | B3: 11036 | C3: 2 | D3: VENDEDOR GENERAL | E3: INSMART TECHNOLOGY SAS | F3: 901703496 | G3: W0414-23 | H3: insmartc@gmail.com | I3: Pago DEL SERVICIO PROG. COWORKING LABS: UN (1) ESPACIO DE TRABAJO (TIPO B) CECO:W0414-23 [MES ABR]. Remitir comprobante de pago a: coordinador.coworking@camaradirecta.com y tesoreria.ccb@camaradirecta.com. Genere su pago exacto sin redondear valores. | J3: ABR | K3: 30 | L3: =('Tarifas - CWL25'!$E$8/1.19)/30 -> 24094.062 | M3: =L3*K3 -> 722821.85 | N3: =M3*1.19 -> 860158 | O3: 46112 | P3: CL 48 28 40 P 2 | Q3: NO
A4: 2 | B4: 11036 | C4: 2 | D4: VENDEDOR GENERAL | E4: SWEETCARE SAS | F4: 901581424 | G4: W0414-24 | H4: contactenos@sweetcare.com.co | I4: Pago DEL SERVICIO PROG. COWORKING LABS: UN (1) ESPACIO DE TRABAJO (TIPO A) CECO:W0414-24 [MES ABR]. Remitir comprobante de pago a: coordinador.coworking@camaradirecta.com y tesoreria.ccb@camaradirecta.com. Genere su pago exacto sin redondear valores. | J4: ABR | K4: 30 | L4: =('Tarifas - CWL25'!$E$7/1.19)/30 -> 14054.874 | M4: =L4*K4 -> 421646.22 | N4: =M4*1.19 -> 501759 | O4: 46112 | P4: CL 48 28 40 P 2 BRR SOTO MAYOR | Q4: SI
A5: 3 | B5: 11036 | C5: 2 | D5: VENDEDOR GENERAL | E5: SOLENIUM SAS | F5: 901097244 | G5: W0414-25 | H5: facturación@solenium.co | I5: Pago DEL SERVICIO PROG. COWORKING LABS: CUATRO (4) ESPACIOS DE TRABAJO (TIPO A) CECO:W0414-25 [MES ABR]. Remitir comprobante de pago a: coordinador.coworking@camaradirecta.com y tesoreria.ccb@camaradirecta.com. Genere su pago exacto sin redondear valores. | J5: ABR | K5: 30 | L5: =('Tarifas - CWL25'!$E$7/1.19*4)/30 -> 56219.496 | M5: =L5*K5 -> 1686584.9 | N5: =M5*1.19 -> 2007036 | O5: 46112 | P5: CL 46 70 A 79 | Q5: NO
A6: 4 | B6: 11036 | C6: 2 | D6: VENDEDOR GENERAL | E6: BFREE ACTIVE TRAVEL SAS | F6: 901815791 | G6: W0414-36 | H6: bfreeactive@gmail.com | I6: Pago DEL SERVICIO PROG. COWORKING LABS: UN (1) ESPACIO DE TRABAJO (TIPO A) CECO:W0414-36 [MES ABR]. Remitir comprobante de pago a: coordinador.coworking@camaradirecta.com y tesoreria.ccb@camaradirecta.com. Genere su pago exacto sin redondear valores. | J6: ABR | K6: 30 | L6: =('Tarifas - CWL25'!$D$7/1.19)/30 -> 10541.148 | M6: =L6*K6 -> 316234.45 | N6: =M6*1.19 -> 376319 | O6: 46112 | P6: AVENIDA BUCAROS CONSEPTO MARCELLA REAL TORRE 5 APARTAMENTO 403 | Q6: NO
A7: 5 | B7: 11036 | C7: 2 | D7: VENDEDOR GENERAL | E7: INDICACION Y DESARROLLO COLOMBIA IDCO SAS | F7: 900816899 | G7: W0414-30 | H7: contabilidad@idco.com.co | I7: Pago DEL SERVICIO PROG. COWORKING LABS: UN (1) ESPACIO DE TRABAJO (TIPO D) CECO:W0414-30 [MES ABR]. Remitir comprobante de pago a: coordinador.coworking@camaradirecta.com y tesoreria.ccb@camaradirecta.com. Genere su pago exacto sin redondear valores. | J7: ABR | K7: 30 | L7: =('Tarifas - CWL25'!$D$10/1.19)/30 -> 52705.742 | M7: =L7*K7 -> 1581172.3 | N7: =M7*1.19 -> 1881595 | O7: 46112 | P7: CL 55 28 25 OF 403 | Q7: NO
A8: 6 | B8: 11036 | C8: 2 | D8: VENDEDOR GENERAL | E8: PROSPECTIVE ING SAS | F8: 901080910 | G8: W0414-31 | H8: infoprospectiveing@gmail.com | I8: Pago DEL SERVICIO PROG. COWORKING LABS: UN (1) ESPACIO DE TRABAJO (TIPO B) CECO:W0414-31 [MES ABR]. Remitir comprobante de pago a: coordinador.coworking@camaradirecta.com y tesoreria.ccb@camaradirecta.com. Genere su pago exacto sin redondear valores. | J8: ABR | K8: 30 | L8: =('Tarifas - CWL25'!D8/1.19)/30 -> 18070.532 | M8: =L8*K8 -> 542115.97 | N8: =M8*1.19 -> 645118 | O8: 46112 | P8: CL 48 28 40 ED INDICA | Q8: SI
A9: 7 | B9: 11036 | C9: 2 | D9: VENDEDOR GENERAL | E9: ESTANDAR & EXCELENCIA SAS BIC | F9: 901818306 | G9: W0414-32 | H9: gerenciaeyesas@gmail.com | I9: Pago DEL SERVICIO PROG. COWORKING LABS: UN (1) ESPACIO DE TRABAJO (TIPO B) CECO:W0414-32 [MES ABR]. Remitir comprobante de pago a: coordinador.coworking@camaradirecta.com y tesoreria.ccb@camaradirecta.com. Genere su pago exacto sin redondear valores. | J9: ABR | K9: 30 | L9: =('Tarifas - CWL25'!D8/1.19)/30 -> 18070.532 | M9: =L9*K9 -> 542115.97 | N9: =M9*1.19 -> 645118 | O9: 46112 | P9: CALLE 18 #25-48 | Q9: NO
A10: 8 | B10: 11036 | C10: 2 | D10: VENDEDOR GENERAL | E10: ENG FORMACION & CONSULTORIA SAS | F10: 901890871 | G10: W0414-33 | H10: gerencia@deelicitaciones.com | I10: Pago DEL SERVICIO PROG. COWORKING LABS: UN (1) ESPACIO DE TRABAJO (TIPO A) CECO:W0414-33 [MES ABR]. Remitir comprobante de pago a: coordinador.coworking@camaradirecta.com y tesoreria.ccb@camaradirecta.com. Genere su pago exacto sin redondear valores. | J10: ABR | K10: 30 | L10: =('Tarifas - CWL25'!D7/1.19)/30 -> 10541.148 | M10: =L10*K10 -> 316234.45 | N10: =M10*1.19 -> 376319 | O10: 46112 | P10: CARRERA 3 #60-80 CASA B4 CONJUNTO VILLAS DE SANTA SOFIA BARRIO LOS NARANJOS | Q10: NO
A11: 9 | B11: 11036 | C11: 2 | D11: VENDEDOR GENERAL | E11: GROUND LIGHTNING SAS | F11: 900759077 | G11: W0414-34 | H11: contabilidad@glground.co | I11: Pago DEL SERVICIO PROG. COWORKING LABS: UN (1) ESPACIO DE TRABAJO (TIPO A) CECO:W0414-34 [MES ABR]. Remitir comprobante de pago a: coordinador.coworking@camaradirecta.com y tesoreria.ccb@camaradirecta.com. Genere su pago exacto sin redondear valores. | J11: ABR | K11: 30 | L11: =M11/30 -> 9604.155 | M11: =(('Tarifas - CWL25'!$C$7/1.19)/30)*8 + (('Tarifas - CWL25'!D7/1.19)/30)*22 -> 288124.65 | N11: =M11*1.19 -> 342868.33 | O11: 46112 | P11: CR 21 55 39 P2 ED MARIA JESUS | Q11: SI
A12: 11 | B12: 11036 | C12: 2 | D12: VENDEDOR GENERAL | E12: FUNDACIÓN ISABERRY | F12: 901988137 | G12: W0414-42 | H12: BUSINESSKIDSBGA@GMAIL.COM | I12: Pago DEL SERVICIO PROG. COWORKING LABS: UN (1) ESPACIO DE TRABAJO (TIPO A) CECO:W0414-42 [MES ABR]. Remitir comprobante de pago a: coordinador.coworking@camaradirecta.com y tesoreria.ccb@camaradirecta.com. Genere su pago exacto sin redondear valores. | J12: ABR | K12: 30 | L12: =('Tarifas - CWL25'!$C$7/1.19)/30 -> 7027.423 | M12: =L12*K12 -> 210822.69 | N12: =M12*1.19 -> 250879 | O12: 46112 | P12: CALLE 48 #28-40 BARRIO SOTOMAYOR | Q12: NO
A13: 12 | B13: 11036 | C13: 2 | D13: VENDEDOR GENERAL | E13: TI&CON | F13: 900748137 | G13: W0414-43 | H13: financiera@ticon.com.co | I13: Pago DEL SERVICIO PROG. COWORKING LABS: UN (1) ESPACIO DE TRABAJO (TIPO A) CECO:W0414-43 [MES ABR]. Remitir comprobante de pago a: coordinador.coworking@camaradirecta.com y tesoreria.ccb@camaradirecta.com. Genere su pago exacto sin redondear valores. | J13: ABR | K13: 30 | L13: =('Tarifas - CWL25'!$C$7/1.19)/30 -> 7027.423 | M13: =L13*K13 -> 210822.69 | N13: =M13*1.19 -> 250879 | O13: 46112 | P13: AV GONZALEZ VALENCIA 55 67 BRR ANTIGUO CAMPESTRE_x000D_ | Q13: NO

Sheet Tarifas - CWL25
B4: AÑO 2025 CWL
B5: TARIFAS 2025 - COWORKING LABS
B6: TIPO DE ESPACIO | C6: TARIFA VERDE (Dcto CCB 50%) | D6: TARIFA AMARILLA (Dcto CCB 25%) | E6: TARIFA BASE 2026
B7: A: Espacio móvil en zona común | C7: 250879 | D7: 376319 | E7: 501759
B8: B: Espacio fijo en cubículo | C8: 430079 | D8: 645118 | E8: 860158
B9: C: Espacio fijo oficina privada x6 | C9: 1003517 | D9: 1505276 | E9: 2007035
B10: D: Espacio fijo oficina privada x7 | C10: 1254397 | D10: 1881595 | E10: 2508794
B11: NOTA: Valores mensules IVA incluido (19%). | D11: 0.0928 | E11: 0.052
B13: TARIFA VERDE (Dcto CCB 50%): | C13: Valor con descuento aplicado por la Cámara de Comercio de Bucaramanga del 50% sobre la tarifa base del año en vigencia. Aplica para el el primer año de vinculación. (12 meses)
B14: TARIFA AMARILLA (Dcto CCB 25%): | C14: Valor con descuento aplicado por la Cámara de Comercio de Bucaramanga del 25% sobre la tarifa base del año en vigencia. Aplica para el el segundo año de vinculación. (12 meses)
B15: TARIFA BASE 2025: | C15: Valor pleno de la tarifa con el aumento aplicado de la variación anual IPC (5,20%) sobre la tarifa base del año anterior. Aplica para el tercer año de vinculación. (12 meses)

Sheet Centros Costo
A1: CENTROS DE COSTOS COWORKING LABS 2025
A2: # | B2: NOMBRE SEGÚN RUT | C2: NIT | D2: CENTROS DE COSTO | E2: NRO. CONTRATO | F2: FECHA INICIO CONTRATO
A3: 1 | B3: INSMART TECHNOLOGY SAS | C3: 901703496 | D3: W0414-23 | E3: 23 | F3: 45717
A4: 2 | B4: SWEETCARE SAS | C4: 901581424 | D4: W0414-24 | E4: 24 | F4: 45717
A5: 3 | B5: SOLENIUM SAS | C5: 901097244 | D5: W0414-25 | E5: 25 | F5: 45717
A6: 4 | B6: GRUPO VIVEX SAS | C6: 901790563 | D6: W0414-26 | E6: 30 | F6: 45717
A7: 5 | B7: NATHALIA CRISTINA VARGAS BETHENCOURT (PN) | C7: 1232888275 | D7: W0414-13 | E7: 16 (2024) | F7: N/A
A8: 6 | B8: SOLUCIONES AMBIENTALES 4R SAS | C8: 901217227 | D8: W0414-27 | E8: 26 | F8: 45717
A9: 7 | B9: BIOFLY SAS BIC | C9: 901653010 | D9: W0414-28 | E9: 27 | F9: 45717
A10: 8 | B10: CORPORACION URBAN PARTICIPATION STAR UP | C10: 901720689 | D10: W0414-15 | E10: 9 (2024) | F10: N/A
A11: 9 | B11: TOTEM BEAR SAS | C11: 901305905 | D11: W0414-17 | E11: 15 (2024) | F11: N/A
A12: 10 | B12: BFREE ACTIVE TRAVEL SAS | C12: 901815791 | D12: W0414-17 | E12: 12 (2024) | F12: N/A
A13: 11 | B13: MULTIPRÉSTAMOS COLOMBIA SAS | C13: 901532644 | D13: W0414-29 | E13: 31 | F13: 45748
A14: 12 | B14: FI INGENIERÍA SAS | C14: 900356176 | D14: W0414-18 | E14: 21 (2024) | F14: N/A
A15: 13 | B15: INNOVACION Y DESARROLLO COLOMBIA IDCO SAS | C15: 900816899 | D15: W0414-30 | E15: 32 | F15: 45748
A16: 14 | B16: PROSPECTIVE ING SAS | C16: 901080910 | D16: W0414-31 | E16: 28 | F16: 45717
A17: 15 | B17: ESTANDAR & EXCELENCIA SAS BIC | C17: 901818306 | D17: W0414-32 | E17: 29 | F17: 45717
A18: 16 | B18: ENG FORMACION & CONSULTORIA SAS | C18: 901890871 | D18: W0414-33 | E18: 33 | F18: 45748
A19: 17 | B19: GROUND LIGHTNING SAS | C19: 900759077 | D19: W0414-34 | E19: 34 | F19: 45756
A20: 18
A21: 19
A22: 20
A23: 21
A24: 22
A25: 23
A26: 24
A27: 25
